{"episode_id": 0, "content_type": "video/mp4", "encoder_version": {"backend": "ffmpeg", "version": "b'ffmpeg version 3.2.4 Copyright (c) 2000-2017 the FFmpeg developers\\nbuilt with Apple LLVM version 8.0.0 (clang-800.0.42.1)\\nconfiguration: --prefix=/usr/local/Cellar/ffmpeg/3.2.4 --enable-shared --enable-pthreads --enable-gpl --enable-version3 --enable-hardcoded-tables --enable-avresample --cc=clang --host-cflags= --host-ldflags= --enable-libmp3lame --enable-libx264 --enable-libxvid --enable-opencl --disable-lzma --enable-vda\\nlibavutil      55. 34.101 / 55. 34.101\\nlibavcodec     57. 64.101 / 57. 64.101\\nlibavformat    57. 56.101 / 57. 56.101\\nlibavdevice    57.  1.100 / 57.  1.100\\nlibavfilter     6. 65.100 /  6. 65.100\\nlibavresample   3.  1.  0 /  3.  1.  0\\nlibswscale      4.  2.100 /  4.  2.100\\nlibswresample   2.  3.100 /  2.  3.100\\nlibpostproc    54.  1.100 / 54.  1.100\\n'", "cmdline": ["ffmpeg", "-nostats", "-loglevel", "error", "-y", "-r", "30", "-f", "rawvideo", "-s:v", "160x210", "-pix_fmt", "rgb24", "-i", "-", "-vcodec", "libx264", "-pix_fmt", "yuv420p", "/Volumes/xs/CodeSpace/AISpace/rl_space/rl_atari_pytorch/Pong-v0_monitor/openaigym.video.0.3438.video000000.mp4"]}}